[
    {
        "id": 30000,
        "answer": "A",
        "error": 1
    },
    {
        "id": 30001,
        "answer": "A",
        "error": 1
    },
    {
        "id": 30002,
        "answer": "A",
        "error": 1
    },
    {
        "id": 30003,
        "answer": "A",
        "error": 1
    },
    {
        "id": 30005,
        "answer": "C",
        "error": 1
    },
    {
        "id": 30011,
        "answer": "A",
        "error": 0
    },
    {
        "id": 30013,
        "answer": "A",
        "error": 1
    },
    {
        "id": 30018,
        "answer": "A",
        "error": 0
    },
    {
        "id": 30019,
        "answer": "C",
        "error": 1
    },
    {
        "id": 30020,
        "answer": "D",
        "error": 0
    },
    {
        "id": 30022,
        "answer": "A",
        "error": 1
    },
    {
        "id": 30023,
        "answer": "A",
        "error": 1
    },
    {
        "id": 30027,
        "answer": "A",
        "error": 1
    },
    {
        "id": 30030,
        "answer": "C",
        "error": 1
    },
    {
        "id": 30031,
        "answer": "C",
        "error": 1
    },
    {
        "id": 30038,
        "answer": "B",
        "error": 1
    },
    {
        "id": 30040,
        "answer": "A",
        "error": 1
    },
    {
        "id": 30042,
        "answer": "D",
        "error": 0
    },
    {
        "id": 30048,
        "answer": "A",
        "error": 1
    },
    {
        "id": 30049,
        "answer": "A",
        "error": 1
    },
    {
        "id": 30052,
        "answer": "D",
        "error": 0
    },
    {
        "id": 30077,
        "answer": "B",
        "error": 0
    },
    {
        "id": 30078,
        "answer": "A",
        "error": 1
    },
    {
        "id": 30082,
        "answer": "C",
        "error": 1
    },
    {
        "id": 30083,
        "answer": "C",
        "error": 1
    },
    {
        "id": 30084,
        "answer": "C",
        "error": 1
    },
    {
        "id": 30086,
        "answer": "A",
        "error": 0
    },
    {
        "id": 30088,
        "answer": "A",
        "error": 1
    },
    {
        "id": 30095,
        "answer": "A",
        "error": 1
    },
    {
        "id": 30102,
        "answer": "B",
        "error": 0
    },
    {
        "id": 30103,
        "answer": "A",
        "error": 1
    },
    {
        "id": 30107,
        "answer": "B",
        "error": 0
    },
    {
        "id": 30112,
        "answer": "A",
        "error": 1
    },
    {
        "id": 30114,
        "answer": "D",
        "error": 1
    },
    {
        "id": 30116,
        "answer": "A",
        "error": 1
    },
    {
        "id": 30117,
        "answer": "B",
        "error": 1
    },
    {
        "id": 30118,
        "answer": "B",
        "error": 1
    },
    {
        "id": 30120,
        "answer": "B",
        "error": 1
    },
    {
        "id": 30121,
        "answer": "C",
        "error": 1
    },
    {
        "id": 30126,
        "answer": "C",
        "error": 1
    },
    {
        "id": 30127,
        "answer": "B",
        "error": 1
    },
    {
        "id": 30128,
        "answer": "C",
        "error": 0
    },
    {
        "id": 30129,
        "answer": "C",
        "error": 0
    },
    {
        "id": 30131,
        "answer": "C",
        "error": 1
    },
    {
        "id": 30132,
        "answer": "A",
        "error": 1
    },
    {
        "id": 30133,
        "answer": "A",
        "error": 1
    },
    {
        "id": 30138,
        "answer": "A",
        "error": 1
    },
    {
        "id": 30139,
        "answer": "A",
        "error": 1
    },
    {
        "id": 30142,
        "answer": "A",
        "error": 1
    },
    {
        "id": 30143,
        "answer": "B",
        "error": 1
    },
    {
        "id": 30145,
        "answer": "A",
        "error": 1
    },
    {
        "id": 30147,
        "answer": "A",
        "error": 1
    },
    {
        "id": 30151,
        "answer": "A",
        "error": 1
    },
    {
        "id": 30153,
        "answer": "A",
        "error": 1
    },
    {
        "id": 30154,
        "answer": "A",
        "error": 1
    },
    {
        "id": 30156,
        "answer": "A",
        "error": 1
    },
    {
        "id": 30157,
        "answer": "A",
        "error": 1
    },
    {
        "id": 30167,
        "answer": "A",
        "error": 1
    },
    {
        "id": 30168,
        "answer": "C",
        "error": 0
    },
    {
        "id": 30169,
        "answer": "D",
        "error": 1
    },
    {
        "id": 30171,
        "answer": "C",
        "error": 1
    },
    {
        "id": 30172,
        "answer": "A",
        "error": 1
    },
    {
        "id": 30180,
        "answer": "B",
        "error": 1
    },
    {
        "id": 30181,
        "answer": "A",
        "error": 1
    },
    {
        "id": 30186,
        "answer": "C",
        "error": 1
    },
    {
        "id": 30187,
        "answer": "A",
        "error": 1
    },
    {
        "id": 30188,
        "answer": "A",
        "error": 0
    },
    {
        "id": 30189,
        "answer": "A",
        "error": 1
    },
    {
        "id": 30190,
        "answer": "B",
        "error": 1
    },
    {
        "id": 30195,
        "answer": "C",
        "error": 1
    },
    {
        "id": 30196,
        "answer": "A",
        "error": 1
    },
    {
        "id": 30198,
        "answer": "C",
        "error": 1
    },
    {
        "id": 30212,
        "answer": "A",
        "error": 0
    },
    {
        "id": 30222,
        "answer": "A",
        "error": 1
    },
    {
        "id": 30224,
        "answer": "B",
        "error": 1
    },
    {
        "id": 30225,
        "answer": "B",
        "error": 1
    },
    {
        "id": 30232,
        "answer": "B",
        "error": 1
    },
    {
        "id": 30234,
        "answer": "C",
        "error": 1
    },
    {
        "id": 30238,
        "answer": "A",
        "error": 1
    },
    {
        "id": 30239,
        "answer": "A",
        "error": 1
    },
    {
        "id": 30241,
        "answer": "A",
        "error": 1
    },
    {
        "id": 30250,
        "answer": "B",
        "error": 0
    },
    {
        "id": 30253,
        "answer": "A",
        "error": 1
    },
    {
        "id": 30254,
        "answer": "A",
        "error": 1
    },
    {
        "id": 30256,
        "answer": "A",
        "error": 1
    },
    {
        "id": 30258,
        "answer": "C",
        "error": 0
    },
    {
        "id": 30259,
        "answer": "A",
        "error": 1
    },
    {
        "id": 30260,
        "answer": "C",
        "error": 0
    },
    {
        "id": 30261,
        "answer": "A",
        "error": 0
    },
    {
        "id": 30262,
        "answer": "A",
        "error": 1
    },
    {
        "id": 30263,
        "answer": "B",
        "error": 1
    },
    {
        "id": 30272,
        "answer": "A",
        "error": 1
    },
    {
        "id": 30275,
        "answer": "A",
        "error": 1
    },
    {
        "id": 30276,
        "answer": "A",
        "error": 1
    },
    {
        "id": 30277,
        "answer": "A",
        "error": 1
    },
    {
        "id": 30281,
        "answer": "B",
        "error": 1
    },
    {
        "id": 30284,
        "answer": "A",
        "error": 1
    },
    {
        "id": 30290,
        "answer": "C",
        "error": 0
    },
    {
        "id": 30291,
        "answer": "A",
        "error": 1
    },
    {
        "id": 30292,
        "answer": "A",
        "error": 1
    },
    {
        "id": 30295,
        "answer": "A",
        "error": 1
    },
    {
        "id": 30297,
        "answer": "C",
        "error": 0
    },
    {
        "id": 30298,
        "answer": "B",
        "error": 1
    },
    {
        "id": 30299,
        "answer": "A",
        "error": 1
    },
    {
        "id": 30301,
        "answer": "D",
        "error": 1
    },
    {
        "id": 30307,
        "answer": "D",
        "error": 1
    },
    {
        "id": 30310,
        "answer": "C",
        "error": 1
    },
    {
        "id": 30312,
        "answer": "A",
        "error": 1
    },
    {
        "id": 30313,
        "answer": "A",
        "error": 1
    },
    {
        "id": 30314,
        "answer": "A",
        "error": 1
    },
    {
        "id": 30318,
        "answer": "B",
        "error": 0
    },
    {
        "id": 30326,
        "answer": "A",
        "error": 1
    },
    {
        "id": 30327,
        "answer": "A",
        "error": 1
    },
    {
        "id": 30329,
        "answer": "C",
        "error": 1
    },
    {
        "id": 30330,
        "answer": "A",
        "error": 1
    },
    {
        "id": 30331,
        "answer": "A",
        "error": 1
    },
    {
        "id": 30333,
        "answer": "A",
        "error": 0
    },
    {
        "id": 30334,
        "answer": "A",
        "error": 1
    },
    {
        "id": 30335,
        "answer": "B",
        "error": 1
    },
    {
        "id": 30336,
        "answer": "D",
        "error": 1
    },
    {
        "id": 30337,
        "answer": "D",
        "error": 1
    },
    {
        "id": 30338,
        "answer": "A",
        "error": 1
    },
    {
        "id": 30339,
        "answer": "C",
        "error": 1
    },
    {
        "id": 30344,
        "answer": "B",
        "error": 0
    },
    {
        "id": 30345,
        "answer": "A",
        "error": 0
    },
    {
        "id": 30346,
        "answer": "A",
        "error": 1
    },
    {
        "id": 30347,
        "answer": "A",
        "error": 1
    },
    {
        "id": 30352,
        "answer": "C",
        "error": 1
    },
    {
        "id": 30354,
        "answer": "A",
        "error": 1
    },
    {
        "id": 30355,
        "answer": "A",
        "error": 1
    },
    {
        "id": 30356,
        "answer": "A",
        "error": 1
    },
    {
        "id": 30358,
        "answer": "C",
        "error": 0
    },
    {
        "id": 30360,
        "answer": "A",
        "error": 1
    },
    {
        "id": 30365,
        "answer": "D",
        "error": 0
    },
    {
        "id": 30366,
        "answer": "A",
        "error": 1
    },
    {
        "id": 30367,
        "answer": "B",
        "error": 0
    },
    {
        "id": 30369,
        "answer": "C",
        "error": 1
    },
    {
        "id": 30371,
        "answer": "A",
        "error": 0
    },
    {
        "id": 30372,
        "answer": "A",
        "error": 1
    },
    {
        "id": 30375,
        "answer": "B",
        "error": 0
    },
    {
        "id": 30379,
        "answer": "A",
        "error": 1
    },
    {
        "id": 30380,
        "answer": "B",
        "error": 1
    },
    {
        "id": 30381,
        "answer": "B",
        "error": 1
    },
    {
        "id": 30382,
        "answer": "B",
        "error": 0
    },
    {
        "id": 30383,
        "answer": "C",
        "error": 0
    },
    {
        "id": 30384,
        "answer": "B",
        "error": 0
    },
    {
        "id": 30388,
        "answer": "D",
        "error": 0
    },
    {
        "id": 30389,
        "answer": "D",
        "error": 0
    },
    {
        "id": 30390,
        "answer": "D",
        "error": 0
    },
    {
        "id": 30392,
        "answer": "A",
        "error": 0
    },
    {
        "id": 30394,
        "answer": "C",
        "error": 0
    },
    {
        "id": 30397,
        "answer": "A",
        "error": 1
    },
    {
        "id": 30399,
        "answer": "B",
        "error": 1
    },
    {
        "id": 30400,
        "answer": "A",
        "error": 0
    },
    {
        "id": 30401,
        "answer": "A",
        "error": 0
    },
    {
        "id": 30402,
        "answer": "A",
        "error": 1
    },
    {
        "id": 30406,
        "answer": "A",
        "error": 1
    },
    {
        "id": 30410,
        "answer": "B",
        "error": 1
    },
    {
        "id": 30411,
        "answer": "C",
        "error": 1
    },
    {
        "id": 30413,
        "answer": "A",
        "error": 1
    },
    {
        "id": 30414,
        "answer": "A",
        "error": 1
    },
    {
        "id": 30417,
        "answer": "A",
        "error": 1
    },
    {
        "id": 30421,
        "answer": "A",
        "error": 1
    },
    {
        "id": 30422,
        "answer": "A",
        "error": 0
    },
    {
        "id": 30432,
        "answer": "D",
        "error": 1
    },
    {
        "id": 30435,
        "answer": "D",
        "error": 1
    },
    {
        "id": 30438,
        "answer": "D",
        "error": 1
    },
    {
        "id": 30442,
        "answer": "D",
        "error": 1
    },
    {
        "id": 30447,
        "answer": "B",
        "error": 1
    },
    {
        "id": 30450,
        "answer": "C",
        "error": 1
    },
    {
        "id": 30451,
        "answer": "A",
        "error": 1
    },
    {
        "id": 30453,
        "answer": "A",
        "error": 1
    },
    {
        "id": 30455,
        "answer": "A",
        "error": 1
    },
    {
        "id": 30456,
        "answer": "C",
        "error": 0
    },
    {
        "id": 30458,
        "answer": "A",
        "error": 1
    },
    {
        "id": 30459,
        "answer": "C",
        "error": 0
    },
    {
        "id": 30460,
        "answer": "A",
        "error": 1
    },
    {
        "id": 30463,
        "answer": "B",
        "error": 0
    },
    {
        "id": 30464,
        "answer": "A",
        "error": 1
    },
    {
        "id": 30466,
        "answer": "A",
        "error": 1
    },
    {
        "id": 30467,
        "answer": "A",
        "error": 1
    },
    {
        "id": 30468,
        "answer": "A",
        "error": 1
    },
    {
        "id": 30471,
        "answer": "D",
        "error": 1
    },
    {
        "id": 30474,
        "answer": "A",
        "error": 1
    },
    {
        "id": 30475,
        "answer": "A",
        "error": 1
    },
    {
        "id": 30476,
        "answer": "B",
        "error": 0
    },
    {
        "id": 30478,
        "answer": "A",
        "error": 1
    },
    {
        "id": 30479,
        "answer": "C",
        "error": 1
    },
    {
        "id": 30480,
        "answer": "C",
        "error": 1
    },
    {
        "id": 30481,
        "answer": "C",
        "error": 1
    },
    {
        "id": 30487,
        "answer": "B",
        "error": 0
    },
    {
        "id": 30490,
        "answer": "C",
        "error": 1
    },
    {
        "id": 30493,
        "answer": "A",
        "error": 1
    },
    {
        "id": 30494,
        "answer": "A",
        "error": 1
    },
    {
        "id": 30495,
        "answer": "A",
        "error": 1
    },
    {
        "id": 30496,
        "answer": "A",
        "error": 1
    },
    {
        "id": 30497,
        "answer": "A",
        "error": 1
    },
    {
        "id": 30498,
        "answer": "A",
        "error": 1
    },
    {
        "id": 30499,
        "answer": "A",
        "error": 1
    },
    {
        "id": 30500,
        "answer": "A",
        "error": 1
    },
    {
        "id": 30501,
        "answer": "A",
        "error": 0
    },
    {
        "id": 30508,
        "answer": "C",
        "error": 0
    },
    {
        "id": 30510,
        "answer": "C",
        "error": 1
    },
    {
        "id": 30514,
        "answer": "A",
        "error": 1
    },
    {
        "id": 30515,
        "answer": "B",
        "error": 0
    },
    {
        "id": 30517,
        "answer": "D",
        "error": 0
    },
    {
        "id": 30518,
        "answer": "A",
        "error": 1
    },
    {
        "id": 30521,
        "answer": "A",
        "error": 1
    },
    {
        "id": 30522,
        "answer": "A",
        "error": 1
    },
    {
        "id": 30523,
        "answer": "A",
        "error": 0
    },
    {
        "id": 30524,
        "answer": "A",
        "error": 1
    },
    {
        "id": 30525,
        "answer": "A",
        "error": 1
    },
    {
        "id": 30530,
        "answer": "A",
        "error": 1
    },
    {
        "id": 30532,
        "answer": "A",
        "error": 1
    },
    {
        "id": 30533,
        "answer": "A",
        "error": 1
    },
    {
        "id": 30535,
        "answer": "D",
        "error": 0
    },
    {
        "id": 30536,
        "answer": "D",
        "error": 1
    },
    {
        "id": 30538,
        "answer": "A",
        "error": 1
    },
    {
        "id": 30539,
        "answer": "A",
        "error": 1
    },
    {
        "id": 30541,
        "answer": "C",
        "error": 0
    },
    {
        "id": 30542,
        "answer": "C",
        "error": 1
    },
    {
        "id": 30543,
        "answer": "C",
        "error": 1
    },
    {
        "id": 30544,
        "answer": "C",
        "error": 1
    },
    {
        "id": 30545,
        "answer": "A",
        "error": 1
    },
    {
        "id": 30546,
        "answer": "B",
        "error": 1
    },
    {
        "id": 30547,
        "answer": "C",
        "error": 0
    },
    {
        "id": 30548,
        "answer": "C",
        "error": 0
    },
    {
        "id": 30550,
        "answer": "D",
        "error": 0
    },
    {
        "id": 30551,
        "answer": "A",
        "error": 1
    },
    {
        "id": 30553,
        "answer": "D",
        "error": 0
    },
    {
        "id": 30557,
        "answer": "A",
        "error": 1
    },
    {
        "id": 30560,
        "answer": "D",
        "error": 1
    },
    {
        "id": 30561,
        "answer": "C",
        "error": 1
    },
    {
        "id": 30562,
        "answer": "D",
        "error": 0
    },
    {
        "id": 30565,
        "answer": "C",
        "error": 0
    },
    {
        "id": 30570,
        "answer": "D",
        "error": 1
    },
    {
        "id": 30572,
        "answer": "B",
        "error": 1
    },
    {
        "id": 30573,
        "answer": "A",
        "error": 1
    },
    {
        "id": 30576,
        "answer": "D",
        "error": 0
    },
    {
        "id": 30578,
        "answer": "A",
        "error": 1
    },
    {
        "id": 30589,
        "answer": "D",
        "error": 0
    },
    {
        "id": 30592,
        "answer": "A",
        "error": 1
    },
    {
        "id": 30593,
        "answer": "D",
        "error": 0
    },
    {
        "id": 30594,
        "answer": "B",
        "error": 0
    },
    {
        "id": 30595,
        "answer": "B",
        "error": 1
    },
    {
        "id": 30599,
        "answer": "A",
        "error": 1
    },
    {
        "id": 30604,
        "answer": "C",
        "error": 1
    },
    {
        "id": 30605,
        "answer": "B",
        "error": 1
    },
    {
        "id": 30609,
        "answer": "A",
        "error": 1
    },
    {
        "id": 30615,
        "answer": "A",
        "error": 1
    },
    {
        "id": 30620,
        "answer": "A",
        "error": 1
    },
    {
        "id": 30621,
        "answer": "A",
        "error": 0
    },
    {
        "id": 30625,
        "answer": "C",
        "error": 0
    },
    {
        "id": 30626,
        "answer": "A",
        "error": 1
    },
    {
        "id": 30628,
        "answer": "D",
        "error": 0
    },
    {
        "id": 30629,
        "answer": "A",
        "error": 1
    },
    {
        "id": 30630,
        "answer": "C",
        "error": 0
    },
    {
        "id": 30631,
        "answer": "A",
        "error": 1
    },
    {
        "id": 30632,
        "answer": "C",
        "error": 0
    },
    {
        "id": 30639,
        "answer": "B",
        "error": 0
    },
    {
        "id": 30641,
        "answer": "C",
        "error": 1
    },
    {
        "id": 30642,
        "answer": "A",
        "error": 1
    },
    {
        "id": 30643,
        "answer": "A",
        "error": 1
    },
    {
        "id": 30650,
        "answer": "A",
        "error": 1
    },
    {
        "id": 30654,
        "answer": "A",
        "error": 1
    },
    {
        "id": 30656,
        "answer": "A",
        "error": 0
    },
    {
        "id": 30658,
        "answer": "C",
        "error": 0
    },
    {
        "id": 30659,
        "answer": "A",
        "error": 1
    },
    {
        "id": 30660,
        "answer": "C",
        "error": 0
    },
    {
        "id": 30662,
        "answer": "D",
        "error": 0
    },
    {
        "id": 30663,
        "answer": "A",
        "error": 1
    },
    {
        "id": 30665,
        "answer": "A",
        "error": 1
    },
    {
        "id": 30668,
        "answer": "A",
        "error": 1
    },
    {
        "id": 30669,
        "answer": "C",
        "error": 0
    },
    {
        "id": 30673,
        "answer": "A",
        "error": 1
    },
    {
        "id": 30674,
        "answer": "A",
        "error": 1
    },
    {
        "id": 30676,
        "answer": "A",
        "error": 1
    },
    {
        "id": 30678,
        "answer": "A",
        "error": 1
    },
    {
        "id": 30682,
        "answer": "A",
        "error": 1
    },
    {
        "id": 30683,
        "answer": "A",
        "error": 1
    },
    {
        "id": 30685,
        "answer": "A",
        "error": 1
    },
    {
        "id": 30686,
        "answer": "A",
        "error": 1
    },
    {
        "id": 30687,
        "answer": "A",
        "error": 1
    },
    {
        "id": 30689,
        "answer": "B",
        "error": 1
    },
    {
        "id": 30691,
        "answer": "A",
        "error": 1
    },
    {
        "id": 30694,
        "answer": "D",
        "error": 0
    },
    {
        "id": 30695,
        "answer": "B",
        "error": 1
    },
    {
        "id": 30696,
        "answer": "A",
        "error": 1
    },
    {
        "id": 30697,
        "answer": "A",
        "error": 1
    },
    {
        "id": 30701,
        "answer": "A",
        "error": 1
    },
    {
        "id": 30709,
        "answer": "A",
        "error": 1
    },
    {
        "id": 30711,
        "answer": "C",
        "error": 1
    },
    {
        "id": 30712,
        "answer": "A",
        "error": 0
    },
    {
        "id": 30713,
        "answer": "B",
        "error": 0
    },
    {
        "id": 30714,
        "answer": "D",
        "error": 1
    },
    {
        "id": 30719,
        "answer": "B",
        "error": 1
    },
    {
        "id": 30727,
        "answer": "A",
        "error": 1
    },
    {
        "id": 30736,
        "answer": "A",
        "error": 1
    },
    {
        "id": 30737,
        "answer": "A",
        "error": 1
    },
    {
        "id": 30738,
        "answer": "D",
        "error": 0
    },
    {
        "id": 30739,
        "answer": "B",
        "error": 0
    },
    {
        "id": 30751,
        "answer": "A",
        "error": 1
    },
    {
        "id": 30754,
        "answer": "C",
        "error": 0
    },
    {
        "id": 30756,
        "answer": "D",
        "error": 0
    },
    {
        "id": 30759,
        "answer": "B",
        "error": 1
    },
    {
        "id": 30761,
        "answer": "D",
        "error": 0
    },
    {
        "id": 30762,
        "answer": "A",
        "error": 1
    },
    {
        "id": 30765,
        "answer": "B",
        "error": 1
    },
    {
        "id": 30766,
        "answer": "D",
        "error": 1
    },
    {
        "id": 30769,
        "answer": "C",
        "error": 0
    },
    {
        "id": 30771,
        "answer": "A",
        "error": 1
    },
    {
        "id": 30772,
        "answer": "A",
        "error": 1
    },
    {
        "id": 30775,
        "answer": "A",
        "error": 1
    },
    {
        "id": 30776,
        "answer": "D",
        "error": 0
    },
    {
        "id": 30777,
        "answer": "B",
        "error": 0
    },
    {
        "id": 30779,
        "answer": "A",
        "error": 1
    },
    {
        "id": 30793,
        "answer": "A",
        "error": 1
    },
    {
        "id": 30797,
        "answer": "A",
        "error": 1
    },
    {
        "id": 30800,
        "answer": "A",
        "error": 1
    },
    {
        "id": 30801,
        "answer": "A",
        "error": 1
    },
    {
        "id": 30802,
        "answer": "D",
        "error": 1
    },
    {
        "id": 30803,
        "answer": "A",
        "error": 1
    },
    {
        "id": 30805,
        "answer": "D",
        "error": 1
    },
    {
        "id": 30820,
        "answer": "A",
        "error": 1
    },
    {
        "id": 30822,
        "answer": "A",
        "error": 1
    },
    {
        "id": 30825,
        "answer": "B",
        "error": 1
    },
    {
        "id": 30826,
        "answer": "B",
        "error": 0
    },
    {
        "id": 30827,
        "answer": "A",
        "error": 1
    },
    {
        "id": 30830,
        "answer": "C",
        "error": 1
    },
    {
        "id": 30832,
        "answer": "B",
        "error": 1
    },
    {
        "id": 30833,
        "answer": "B",
        "error": 1
    },
    {
        "id": 30842,
        "answer": "C",
        "error": 1
    },
    {
        "id": 30843,
        "answer": "C",
        "error": 1
    },
    {
        "id": 30846,
        "answer": "C",
        "error": 1
    },
    {
        "id": 30847,
        "answer": "C",
        "error": 1
    },
    {
        "id": 30848,
        "answer": "D",
        "error": 0
    },
    {
        "id": 30850,
        "answer": "C",
        "error": 1
    },
    {
        "id": 30851,
        "answer": "A",
        "error": 0
    },
    {
        "id": 30853,
        "answer": "A",
        "error": 1
    },
    {
        "id": 30854,
        "answer": "A",
        "error": 1
    },
    {
        "id": 30873,
        "answer": "C",
        "error": 1
    },
    {
        "id": 30875,
        "answer": "C",
        "error": 0
    },
    {
        "id": 30877,
        "answer": "A",
        "error": 1
    },
    {
        "id": 30879,
        "answer": "B",
        "error": 1
    },
    {
        "id": 30882,
        "answer": "D",
        "error": 0
    },
    {
        "id": 30883,
        "answer": "A",
        "error": 1
    },
    {
        "id": 30885,
        "answer": "C",
        "error": 1
    },
    {
        "id": 30887,
        "answer": "D",
        "error": 1
    },
    {
        "id": 30888,
        "answer": "D",
        "error": 1
    },
    {
        "id": 30893,
        "answer": "A",
        "error": 0
    },
    {
        "id": 30895,
        "answer": "A",
        "error": 1
    },
    {
        "id": 30896,
        "answer": "A",
        "error": 1
    },
    {
        "id": 30899,
        "answer": "C",
        "error": 1
    },
    {
        "id": 30902,
        "answer": "A",
        "error": 1
    },
    {
        "id": 30904,
        "answer": "A",
        "error": 1
    },
    {
        "id": 30906,
        "answer": "A",
        "error": 1
    },
    {
        "id": 30907,
        "answer": "A",
        "error": 1
    },
    {
        "id": 30910,
        "answer": "A",
        "error": 1
    },
    {
        "id": 30914,
        "answer": "A",
        "error": 1
    },
    {
        "id": 30918,
        "answer": "C",
        "error": 1
    },
    {
        "id": 30921,
        "answer": "D",
        "error": 1
    },
    {
        "id": 30925,
        "answer": "D",
        "error": 1
    },
    {
        "id": 30926,
        "answer": "A",
        "error": 0
    },
    {
        "id": 30933,
        "answer": "C",
        "error": 1
    },
    {
        "id": 30935,
        "answer": "C",
        "error": 1
    },
    {
        "id": 30936,
        "answer": "C",
        "error": 1
    },
    {
        "id": 30939,
        "answer": "B",
        "error": 1
    },
    {
        "id": 30941,
        "answer": "B",
        "error": 1
    },
    {
        "id": 30942,
        "answer": "B",
        "error": 0
    },
    {
        "id": 30943,
        "answer": "C",
        "error": 0
    },
    {
        "id": 30946,
        "answer": "A",
        "error": 1
    },
    {
        "id": 30947,
        "answer": "B",
        "error": 1
    },
    {
        "id": 30951,
        "answer": "A",
        "error": 1
    },
    {
        "id": 30958,
        "answer": "A",
        "error": 1
    },
    {
        "id": 30959,
        "answer": "D",
        "error": 0
    },
    {
        "id": 30960,
        "answer": "A",
        "error": 1
    },
    {
        "id": 30967,
        "answer": "A",
        "error": 0
    },
    {
        "id": 30968,
        "answer": "D",
        "error": 0
    },
    {
        "id": 30969,
        "answer": "B",
        "error": 1
    },
    {
        "id": 30975,
        "answer": "A",
        "error": 1
    },
    {
        "id": 30980,
        "answer": "A",
        "error": 1
    },
    {
        "id": 30981,
        "answer": "B",
        "error": 0
    },
    {
        "id": 30984,
        "answer": "A",
        "error": 1
    },
    {
        "id": 30985,
        "answer": "A",
        "error": 0
    },
    {
        "id": 30987,
        "answer": "A",
        "error": 1
    },
    {
        "id": 30988,
        "answer": "A",
        "error": 1
    },
    {
        "id": 30989,
        "answer": "A",
        "error": 1
    },
    {
        "id": 30991,
        "answer": "A",
        "error": 1
    },
    {
        "id": 30997,
        "answer": "A",
        "error": 0
    },
    {
        "id": 31004,
        "answer": "D",
        "error": 0
    },
    {
        "id": 31005,
        "answer": "A",
        "error": 1
    },
    {
        "id": 31006,
        "answer": "A",
        "error": 0
    },
    {
        "id": 31008,
        "answer": "A",
        "error": 1
    },
    {
        "id": 31011,
        "answer": "A",
        "error": 0
    },
    {
        "id": 31013,
        "answer": "A",
        "error": 1
    },
    {
        "id": 31015,
        "answer": "A",
        "error": 0
    },
    {
        "id": 31016,
        "answer": "C",
        "error": 0
    },
    {
        "id": 31017,
        "answer": "A",
        "error": 1
    },
    {
        "id": 31018,
        "answer": "D",
        "error": 0
    },
    {
        "id": 31020,
        "answer": "C",
        "error": 1
    },
    {
        "id": 31022,
        "answer": "A",
        "error": 0
    },
    {
        "id": 31024,
        "answer": "A",
        "error": 1
    },
    {
        "id": 31025,
        "answer": "A",
        "error": 1
    },
    {
        "id": 31028,
        "answer": "A",
        "error": 1
    },
    {
        "id": 31030,
        "answer": "A",
        "error": 1
    },
    {
        "id": 31033,
        "answer": "B",
        "error": 1
    },
    {
        "id": 31034,
        "answer": "C",
        "error": 0
    },
    {
        "id": 31040,
        "answer": "A",
        "error": 1
    },
    {
        "id": 31041,
        "answer": "D",
        "error": 1
    },
    {
        "id": 31046,
        "answer": "C",
        "error": 1
    },
    {
        "id": 31047,
        "answer": "B",
        "error": 1
    },
    {
        "id": 31059,
        "answer": "A",
        "error": 1
    },
    {
        "id": 31065,
        "answer": "A",
        "error": 1
    },
    {
        "id": 31072,
        "answer": "D",
        "error": 1
    },
    {
        "id": 31074,
        "answer": "D",
        "error": 0
    },
    {
        "id": 31075,
        "answer": "A",
        "error": 1
    },
    {
        "id": 31076,
        "answer": "A",
        "error": 1
    },
    {
        "id": 31079,
        "answer": "A",
        "error": 1
    },
    {
        "id": 31080,
        "answer": "D",
        "error": 0
    },
    {
        "id": 31081,
        "answer": "A",
        "error": 1
    }
]